{
  "project_info": {
    "project_number": "316233595325",
    "firebase_url": "https://bmicalculator-f6c7f.firebaseio.com",
    "project_id": "bmicalculator-f6c7f",
    "storage_bucket": "bmicalculator-f6c7f.appspot.com"
  },
  "client": [
    {
      "client_info": {
        "mobilesdk_app_id": "1:316233595325:android:d1e4cb3df410f6d2fc3ad4",
        "android_client_info": {
          "package_name": "com.nishant.bmi"
        }
      },
      "oauth_client": [
        {
          "client_id": "316233595325-odubbib9q9ruo0e72ketvnnqni2fuv68.apps.googleusercontent.com",
          "client_type": 3
        }
      ],
      "api_key": [
        {
          "current_key": "AIzaSyD8RHynNUHR8iy86sCC3rj7QshO39_uyvs"
        }
      ],
      "services": {
        "appinvite_service": {
          "other_platform_oauth_client": [
            {
              "client_id": "316233595325-odubbib9q9ruo0e72ketvnnqni2fuv68.apps.googleusercontent.com",
              "client_type": 3
            }
          ]
        }
      }
    }
  ],
  "configuration_version": "1"
}